hex_robo_yoco/__init__.py
hex_robo_yoco/hex_yoco_archer_y6.py
hex_robo_yoco/hex_yoco_e3_desktop.py
hex_robo_yoco/drivers/archer_y6_driver.py
hex_robo_yoco/drivers/e3_desktop_driver.py
hex_robo_yoco-0.0.6.dist-info/licenses/LICENSE
hex_robo_yoco-0.0.6.dist-info/METADATA
hex_robo_yoco-0.0.6.dist-info/WHEEL
hex_robo_yoco-0.0.6.dist-info/top_level.txt
hex_robo_yoco-0.0.6.dist-info/RECORD
