Metadata-Version: 2.4
Name: hex_robo_yoco
Version: 0.0.6
Summary: HEXFELLOW YOCO
Author-email: Dong Zhaorui <joray.dong@hexfellow.com>
Maintainer-email: jecjune <zejun.chen@hexfellow.com>, Dong Zhaorui <joray.dong@hexfellow.com>
License-Expression: Apache-2.0
Project-URL: Homepage, https://github.com/hexfellow/hex_robo_yoco
Project-URL: Repository, https://github.com/hexfellow/hex_robo_yoco.git
Project-URL: Bug Tracker, https://github.com/hexfellow/hex_robo_yoco/issues
Project-URL: Documentation, https://github.com/hexfellow/hex_robo_yoco/wiki
Keywords: hex_robo_yoco
Classifier: Development Status :: 4 - Beta
Classifier: Intended Audience :: Developers
Classifier: Intended Audience :: Science/Research
Classifier: Topic :: Software Development :: Libraries :: Python Modules
Classifier: Programming Language :: Python :: 3
Classifier: Programming Language :: Python :: 3.10
Classifier: Programming Language :: Python :: 3.11
Classifier: Programming Language :: Python :: 3.12
Classifier: Operating System :: POSIX :: Linux
Requires-Python: >=3.8
License-File: LICENSE
Requires-Dist: hex_zmq_servers[mujoco]<0.4.0,>=0.3.0
Dynamic: license-file
